[
    {
        "dark": "#F03F35",
        "light": "#B6E3E4"
    },
    {
        "dark": "#EF3D4A",
        "light": "#96CBD1"
    },
    {
        "dark": "#015397",
        "light": "#FD4344"
    },
    {
        "dark": "#D83530",
        "light": "#0BBCD6"
    },
    {
        "dark": "#1B1D1C",
        "light": "#EA1821"
    },
    {
        "dark": "#28292B",
        "light": "#FF0046"
    },
    {
        "dark": "#FF4552",
        "light": "#EFE8D8"
    },
    {
        "dark": "#FD667C",
        "light": "#CFD1DD"
    },
    {
        "dark": "#19227D",
        "light": "#F1C2B8"
    },
    {
        "dark": "#162BF4",
        "light": "#EEC0DB"
    },
    {
        "dark": "#2D1FE8",
        "light": "#BEA1A5"
    },
    {
        "dark": "#16C37B",
        "light": "#F4F4F4"
    },
    {
        "dark": "#0E39B1",
        "light": "#FFFFFF"
    },
    {
        "dark": "#1B1D1C",
        "light": "#A6CFE2"
    },
    {
        "dark": "#371722",
        "light": "#BBAB9B"
    },
    {
        "dark": "#008E8F",
        "light": "#C7C6C4"
    },
    {
        "dark": "#CF2F88",
        "light": "#DABAAF"
    },
    {
        "dark": "#C02A1A",
        "light": "#B6CABF"
    },
    {
        "dark": "#B32B48",
        "light": "#C5BEAA"
    },
    {
        "dark": "#D31B33",
        "light": "#FDF06E"
    },
    {
        "dark": "#D13642",
        "light": "#FDEDB2"
    },
    {
        "dark": "#2A3571",
        "light": "#1EC3BD"
    },
    {
        "dark": "#181A27",
        "light": "#E88565"
    },
    {
        "dark": "#018FD3",
        "light": "#F4C7EE"
    },
    {
        "dark": "#1B1D1C",
        "light": "#77EEDF"
    },
    {
        "dark": "#1EC8A9",
        "light": "#FFEFE5"
    },
    {
        "dark": "#28292B",
        "light": "#B1FDEA"
    },
    {
        "dark": "#28292B",
        "light": "#E57066"
    },
    {
        "dark": "#28292B",
        "light": "#EED974"
    },
    {
        "dark": "#0A64C0",
        "light": "#FBFE55"
    },
    {
        "dark": "#168E96",
        "light": "#FDE2C8"
    },
    {
        "dark": "#21AD65",
        "light": "#FEC8BE"
    },
    {
        "dark": "#E44A66",
        "light": "#D3E8E1"
    },
    {
        "dark": "#4F3A4B",
        "light": "#E75151"
    },
    {
        "dark": "#112378",
        "light": "#FBECCF"
    },
    {
        "dark": "#01B28B",
        "light": "#F5CCCF"
    },
    {
        "dark": "#1B1D1C",
        "light": "#9257A9"
    },
    {
        "dark": "#FF5034",
        "light": "#C6D7C7"
    },
    {
        "dark": "#481B19",
        "light": "#F02F3B"
    },
    {
        "dark": "#169BA3",
        "light": "#FFFDE7"
    },
    {
        "dark": "#1539CF",
        "light": "#F1D3D3"
    },
    {
        "dark": "#FF2B93",
        "light": "#7CE0E6"
    },
    {
        "dark": "#3B755F",
        "light": "#F2CB6C"
    },
    {
        "dark": "#D36479",
        "light": "#85CEBA"
    },
    {
        "dark": "#481B19",
        "light": "#9B8FFF"
    },
    {
        "dark": "#0D3934",
        "light": "#FFC5D6"
    },
    {
        "dark": "#062AFA",
        "light": "#BBFFBA"
    },
    {
        "dark": "#5E30CF",
        "light": "#99FFD0"
    },
    {
        "dark": "#1A0BCA",
        "light": "#FB9B2A"
    },
    {
        "dark": "#F6748D",
        "light": "#E5E8DC"
    },
    {
        "dark": "#073EA7",
        "light": "#90FFE4"
    },
    {
        "dark": "#643387",
        "light": "#F3735C"
    },
    {
        "dark": "#009BC6",
        "light": "#FFD15E"
    },
    {
        "dark": "#202448",
        "light": "#A48641"
    },
    {
        "dark": "#181E46",
        "light": "#D17C78"
    },
    {
        "dark": "#0A506B",
        "light": "#FEBA02"
    },
    {
        "dark": "#0E2F56",
        "light": "#FC3B2D"
    },
    {
        "dark": "#6136BA",
        "light": "#00FFC3"
    },
    {
        "dark": "#54120A",
        "light": "#EF5B0B"
    },
    {
        "dark": "#DE10DE",
        "light": "#FFD100"
    },
    {
        "dark": "#32145D",
        "light": "#FF8C8B"
    },
    {
        "dark": "#1429C7",
        "light": "#FF4D06"
    },
    {
        "dark": "#1405FF",
        "light": "#CDFF05"
    },
    {
        "dark": "#1E3B34",
        "light": "#FEBC00"
    },
    {
        "dark": "#1E3B34",
        "light": "#E10000"
    },
    {
        "dark": "#112378",
        "light": "#F64A00"
    },
    {
        "dark": "#2C159D",
        "light": "#C39D63"
    },
    {
        "dark": "#8C23FF",
        "light": "#00FDFF"
    },
    {
        "dark": "#B03297",
        "light": "#95D0FF"
    },
    {
        "dark": "#44266D",
        "light": "#14E1E3"
    },
    {
        "dark": "#1E3B34",
        "light": "#FF6B61"
    },
    {
        "dark": "#502F7E",
        "light": "#EDB200"
    },
    {
        "dark": "#CD244A",
        "light": "#EAC417"
    },
    {
        "dark": "#6136BA",
        "light": "#DABAAF"
    },
    {
        "dark": "#1B1D1C",
        "light": "#F1B908"
    },
    {
        "dark": "#E5270E",
        "light": "#7EBDC1"
    },
    {
        "dark": "#F31354",
        "light": "#12E2BA"
    },
    {
        "dark": "#266691",
        "light": "#FD6749"
    },
    {
        "dark": "#B8237E",
        "light": "#6DA1AE"
    },
    {
        "dark": "#CC2E22",
        "light": "#FFB812"
    },
    {
        "dark": "#6614C8",
        "light": "#DFDC02"
    },
    {
        "dark": "#28292B",
        "light": "#A646A7"
    },
    {
        "dark": "#586C74",
        "light": "#D2DB00"
    },
    {
        "dark": "#6614C8",
        "light": "#F25A10"
    },
    {
        "dark": "#1E3B34",
        "light": "#FF8C8B"
    },
    {
        "dark": "#FF5100",
        "light": "#B3E129"
    },
    {
        "dark": "#821E74",
        "light": "#FF8C8B"
    },
    {
        "dark": "#7912D9",
        "light": "#E289DE"
    },
    {
        "dark": "#C43253",
        "light": "#D3B738"
    },
    {
        "dark": "#F7CE17",
        "light": "#2B64A9"
    },
    {
        "dark": "#FC6C11",
        "light": "#1E3B34"
    },
    {
        "dark": "#F7CE17",
        "light": "#B8237E"
    }
]